fimeval/__init__.py
fimeval/setup_benchFIM.py
fimeval/utilis.py
fimeval/BenchFIMQuery/__init__.py
fimeval/BenchFIMQuery/access_benchfim.py
fimeval/BenchFIMQuery/utilis.py
fimeval/BuildingFootprint/__init__.py
fimeval/BuildingFootprint/evaluationwithBF.py
fimeval/BuildingFootprint/microsoftBF.py
fimeval/ContingencyMap/PWBs3.py
fimeval/ContingencyMap/__init__.py
fimeval/ContingencyMap/evaluationFIM.py
fimeval/ContingencyMap/methods.py
fimeval/ContingencyMap/metrics.py
fimeval/ContingencyMap/plotevaluationmetrics.py
fimeval/ContingencyMap/printcontingency.py
fimeval-0.1.57.dist-info/licenses/LICENSE.txt
fimeval-0.1.57.dist-info/METADATA
fimeval-0.1.57.dist-info/WHEEL
fimeval-0.1.57.dist-info/top_level.txt
fimeval-0.1.57.dist-info/RECORD
